<?xml version="1.0" encoding="utf-8" ?><dwsync><file name="bx_loader.gif" server="66.96.147.221//" local="3436888212" remote="3502821360" Dst="-1" /><file name="controls-aqua.png" server="66.96.147.221//" local="3479567706" remote="3502821360" Dst="-1" /><file name="controls-blue.png" server="66.96.147.221//" local="3450592642" remote="3502821360" Dst="-1" /><file name="controls-brown.png" server="66.96.147.221//" local="3479567636" remote="3502821360" Dst="-1" /><file name="controls-dark-blue.png" server="66.96.147.221//" local="3479567178" remote="3502821360" Dst="-1" /><file name="controls-light-green.png" server="66.96.147.221//" local="3479567416" remote="3502821360" Dst="-1" /><file name="controls-light.png" server="66.96.147.221//" local="3452534926" remote="3502821360" Dst="-1" /><file name="controls-orange.png" server="66.96.147.221//" local="3452101828" remote="3502821360" Dst="-1" /><file name="controls-purple.png" server="66.96.147.221//" local="3479567318" remote="3502821360" Dst="-1" /><file name="controls-red.png" server="66.96.147.221//" local="3452101890" remote="3502821360" Dst="-1" /><file name="controls.png" server="66.96.147.221//" local="3443964364" remote="3502821360" Dst="-1" /></dwsync>